CHANGES.rst
MANIFEST.in
README.rst
setup.cfg
setup.py
khufu_javascript/__init__.py
khufu_javascript/tests.py
khufu_javascript/utils.py
khufu_javascript.egg-info/PKG-INFO
khufu_javascript.egg-info/SOURCES.txt
khufu_javascript.egg-info/dependency_links.txt
khufu_javascript.egg-info/top_level.txt
khufu_javascript.egg-info/zip-safe
khufu_javascript/dojo/__init__.py
khufu_javascript/dojo/tests.py
khufu_javascript/dojo/testscript.js