Metadata-Version: 1.0
Name: khufu-javascript
Version: 0.1
Summary: Khufu/Pyramid component for managing javascript resources
Home-page: UNKNOWN
Author: Rocky Burt
Author-email: rocky@serverzen.com
License: BSD
Keywords: khufu pyramid pylons
Platform: UNKNOWN
